forthright_django/__init__.py
forthright_django/admin.py
forthright_django/apps.py
forthright_django/forthright_client.py
forthright_django/forthright_server.py
forthright_django/models.py
forthright_django/tests.py
forthright_django/urls.py
forthright_django/views.py
forthright_django/migrations/__init__.py
forthright_django-0.0.6.dist-info/LICENSE
forthright_django-0.0.6.dist-info/METADATA
forthright_django-0.0.6.dist-info/WHEEL
forthright_django-0.0.6.dist-info/top_level.txt
forthright_django-0.0.6.dist-info/RECORD
